[
  {
    "speaker": "カルド先生",
    "text": "本日より、君には実戦理術の基礎を学んでもらう。"
  },
  {
    "speaker": "リカ",
    "text": "はい！ ……えっと、先生。黒板の文字、半分くらい読めません！"
  },
  {
    "speaker": "モル",
    "text": "半分読めたら天才モル。"
  },
  {
    "speaker": "カルド先生",
    "text": "問題ない。最初から式を読む必要はない。読めない式は、まず触れればいい。"
  },
  {
    "speaker": "モル",
    "text": "触るとたまに爆発するモル。"
  },
  {
    "speaker": "リカ",
    "text": "それは先に言って！？"
  },
  {
    "speaker": "カルド先生",
    "text": "魔法とは、世界の式に“余白”を見つけ、そこへ式力を代入する技術だ。"
  },
  {
    "speaker": "リカ",
    "text": "……すみません。もう一回、短くお願いします。"
  },
  {
    "speaker": "カルド先生",
    "text": "世界には、少しだけ書き足せる場所がある。"
  },
  {
    "speaker": "モル",
    "text": "□に力を入れるモル。"
  },
  {
    "speaker": "リカ",
    "text": "あ、それならわかる！"
  },
  {
    "speaker": "カルド先生",
    "text": "ちょうどいい。あのぷよ魔を押してみろ。"
  },
  {
    "speaker": "モル",
    "text": "軽いなら押せるモル！"
  },
  {
    "speaker": "カルド先生",
    "text": "重いものは、動かしにくい。今日はそれだけ覚えればいい。"
  }
]